{"asset/bg_app.png":["asset/bg_app.png"],"asset/fashion.png":["asset/fashion.png"],"asset/ic_launcher.png":["asset/ic_launcher.png"],"asset/keys/0_key.png":["asset/keys/0_key.png"],"asset/keys/10_key.png":["asset/keys/10_key.png"],"asset/keys/11_key.png":["asset/keys/11_key.png"],"asset/keys/12_key.png":["asset/keys/12_key.png"],"asset/keys/13_key.png":["asset/keys/13_key.png"],"asset/keys/14_key.png":["asset/keys/14_key.png"],"asset/keys/15_key.png":["asset/keys/15_key.png"],"asset/keys/16_key.png":["asset/keys/16_key.png"],"asset/keys/17_key.png":["asset/keys/17_key.png"],"asset/keys/18_key.png":["asset/keys/18_key.png"],"asset/keys/19_key.png":["asset/keys/19_key.png"],"asset/keys/1_key.png":["asset/keys/1_key.png"],"asset/keys/20_key.png":["asset/keys/20_key.png"],"asset/keys/21_key.png":["asset/keys/21_key.png"],"asset/keys/22_key.png":["asset/keys/22_key.png"],"asset/keys/23_key.png":["asset/keys/23_key.png"],"asset/keys/24_key.png":["asset/keys/24_key.png"],"asset/keys/25_key.png":["asset/keys/25_key.png"],"asset/keys/26_key.png":["asset/keys/26_key.png"],"asset/keys/27_key.png":["asset/keys/27_key.png"],"asset/keys/28_key.png":["asset/keys/28_key.png"],"asset/keys/29_key.png":["asset/keys/29_key.png"],"asset/keys/2_key.png":["asset/keys/2_key.png"],"asset/keys/30_key.png":["asset/keys/30_key.png"],"asset/keys/31_key.png":["asset/keys/31_key.png"],"asset/keys/32_key.png":["asset/keys/32_key.png"],"asset/keys/33_key.png":["asset/keys/33_key.png"],"asset/keys/34_key.png":["asset/keys/34_key.png"],"asset/keys/35_key.png":["asset/keys/35_key.png"],"asset/keys/3_key.png":["asset/keys/3_key.png"],"asset/keys/4_key.png":["asset/keys/4_key.png"],"asset/keys/5_key.png":["asset/keys/5_key.png"],"asset/keys/6_key.png":["asset/keys/6_key.png"],"asset/keys/7_key.png":["asset/keys/7_key.png"],"asset/keys/8_key.png":["asset/keys/8_key.png"],"asset/keys/9_key.png":["asset/keys/9_key.png"],"asset/white_icon.png":["asset/white_icon.png"],"packages/cupertino_icons/assets/CupertinoIcons.ttf":["packages/cupertino_icons/assets/CupertinoIcons.ttf"],"packages/wakelock_web/assets/no_sleep.js":["packages/wakelock_web/assets/no_sleep.js"]}